devforge/__init__.py
devforge/__main__.py
devforge/cli.py
devforge/core/__init__.py
devforge/core/custom_generator.py
devforge/utils/__init__.py
devforge-1.1.1.dist-info/licenses/LICENSE
testapp/backend/main.py
tests/test_structure.py
devforge-1.1.1.dist-info/METADATA
devforge-1.1.1.dist-info/WHEEL
devforge-1.1.1.dist-info/entry_points.txt
devforge-1.1.1.dist-info/top_level.txt
devforge-1.1.1.dist-info/RECORD
